presto_types_parser/__init__.py
presto_types_parser/src/__init__.py
presto_types_parser/src/row_parser.py
presto_types_parser/src/row_parser_builder.py
presto_types_parser/src/row_parsing_exception.py
presto_types_parser/src/column_process/__init__.py
presto_types_parser/src/column_process/default_cell_processor.py
presto_types_parser/src/column_process/varbinary_processor.py
presto_types_parser/src/complex_column_process/__init__.py
presto_types_parser/src/complex_column_process/array_processor.py
presto_types_parser/src/complex_column_process/array_processor_builder.py
presto_types_parser/src/complex_column_process/inner_row_processor.py
presto_types_parser/src/complex_column_process/inner_row_processor_builder.py
presto_types_parser/src/complex_column_process/map_processor.py
presto_types_parser/src/complex_column_process/map_processor_builder.py
presto_types_parser/tests/column_process/__init__.py
presto_types_parser/tests/column_process/test_default_column_processor.py
presto_types_parser/tests/column_process/test_varbinary_processor.py
presto_types_parser/tests/complex_column_process/__init__.py
presto_types_parser/tests/complex_column_process/test_array_processor.py
presto_types_parser/tests/complex_column_process/test_array_processor_builder.py
presto_types_parser/tests/complex_column_process/test_inner_row_processor.py
presto_types_parser/tests/complex_column_process/test_inner_row_processor_builder.py
presto_types_parser/tests/complex_column_process/test_map_processor.py
presto_types_parser/tests/complex_column_process/test_map_processor_builder.py
presto_types_parser-0.0.2.dist-info/LICENSE
presto_types_parser-0.0.2.dist-info/METADATA
presto_types_parser-0.0.2.dist-info/WHEEL
presto_types_parser-0.0.2.dist-info/top_level.txt
presto_types_parser-0.0.2.dist-info/RECORD
